flexai/__init__.py
flexai/agent.py
flexai/capability.py
flexai/message.py
flexai/py.typed
flexai/tool.py
flexai/capabilities/__init__.py
flexai/capabilities/add_context.py
flexai/capabilities/limit_tool_use.py
flexai/capabilities/truncate_messages.py
flexai/llm/__init__.py
flexai/llm/anthropic.py
flexai/llm/client.py
flexai/llm/exceptions.py
flexai/llm/gemini.py
flexai/llm/openai.py
flexai/llm/openai_responses.py
reflex_agent-0.1.44.dist-info/METADATA
reflex_agent-0.1.44.dist-info/WHEEL
reflex_agent-0.1.44.dist-info/RECORD
