Metadata-Version: 2.4
Name: reflex-agent
Version: 0.1.44
Summary: A flexible agent framework.
Author-email: Nikhil Rao <nikhil@reflex.dev>
Requires-Python: >=3.10
Provides-Extra: anthropic
Requires-Dist: anthropic>=0.42.0; extra == 'anthropic'
Provides-Extra: gemini
Requires-Dist: google-genai>=1.9.0; extra == 'gemini'
Provides-Extra: litellm
Requires-Dist: litellm>=1.55.0; extra == 'litellm'
Provides-Extra: openai
Requires-Dist: openai>=1.63.2; extra == 'openai'
